pyconfigevents/__init__.py
pyconfigevents/event_handler.py
pyconfigevents/model.py
pyconfigevents/utils/file.py
pyconfigevents/utils/read_file.py
pyconfigevents/utils/save_file.py
pyconfigevents-0.2.0.dist-info/licenses/LICENSE
pyconfigevents-0.2.0.dist-info/METADATA
pyconfigevents-0.2.0.dist-info/WHEEL
pyconfigevents-0.2.0.dist-info/top_level.txt
pyconfigevents-0.2.0.dist-info/RECORD
