Metadata-Version: 2.4
Name: PyConfigEvents
Version: 0.2.0
Summary: PyConfigEvents 是一个基于 Pydantic 的配置管理库，提供了事件驱动的配置变更通知机制。它允许您创建类型安全的配置模型，并在配置值变化时自动触发回调函数。
Author-email: Nann <18906571516@163.com>
License-Expression: MIT
Project-URL: Homepage, https://github.com/JunNanLYS/PyConfigEvents
Project-URL: Issues, https://github.com/JunNanLYS/PyConfigEvents/issues
Requires-Python: >=3.12
License-File: LICENSE
Requires-Dist: pydantic>=2.11.4
Requires-Dist: pytest>=8.3.5
Requires-Dist: pytomlpp>=1.0.13
Requires-Dist: pyyaml>=6.0.2
Requires-Dist: watchdog>=6.0.0
Provides-Extra: test
Requires-Dist: pytest>=8.3.5; extra == "test"
Dynamic: license-file
